inspect_scout/.gitignore
inspect_scout/__init__.py
inspect_scout/_scan.py
inspect_scout/_scancontext.py
inspect_scout/_scanjob.py
inspect_scout/_scanjob_config.py
inspect_scout/_scanlist.py
inspect_scout/_scanresults.py
inspect_scout/_scanspec.py
inspect_scout/_version.py
inspect_scout/py.typed
inspect_scout/_cli/__init__.py
inspect_scout/_cli/common.py
inspect_scout/_cli/db.py
inspect_scout/_cli/info.py
inspect_scout/_cli/main.py
inspect_scout/_cli/scan.py
inspect_scout/_cli/scan_complete.py
inspect_scout/_cli/scan_list.py
inspect_scout/_cli/scan_resume.py
inspect_scout/_cli/scan_status.py
inspect_scout/_cli/trace.py
inspect_scout/_cli/view.py
inspect_scout/_concurrency/__init__.py
inspect_scout/_concurrency/_iterator.py
inspect_scout/_concurrency/_mp_common.py
inspect_scout/_concurrency/_mp_logging.py
inspect_scout/_concurrency/_mp_registry.py
inspect_scout/_concurrency/_mp_semaphore.py
inspect_scout/_concurrency/_mp_shutdown.py
inspect_scout/_concurrency/_mp_subprocess.py
inspect_scout/_concurrency/common.py
inspect_scout/_concurrency/multi_process.py
inspect_scout/_concurrency/single_process.py
inspect_scout/_display/__init__.py
inspect_scout/_display/_display.py
inspect_scout/_display/log.py
inspect_scout/_display/none.py
inspect_scout/_display/plain.py
inspect_scout/_display/protocol.py
inspect_scout/_display/rich.py
inspect_scout/_display/util.py
inspect_scout/_grep_scanner/__init__.py
inspect_scout/_grep_scanner/_event.py
inspect_scout/_grep_scanner/_grep_scanner.py
inspect_scout/_grep_scanner/_match.py
inspect_scout/_llm_scanner/__init__.py
inspect_scout/_llm_scanner/_llm_scanner.py
inspect_scout/_llm_scanner/answer.py
inspect_scout/_llm_scanner/params.py
inspect_scout/_llm_scanner/prompt.py
inspect_scout/_llm_scanner/structured.py
inspect_scout/_llm_scanner/types.py
inspect_scout/_observe/__init__.py
inspect_scout/_observe/_observe.py
inspect_scout/_observe/context.py
inspect_scout/_observe/message_ids.py
inspect_scout/_observe/providers/__init__.py
inspect_scout-0.4.11.dist-info/METADATA
inspect_scout-0.4.11.dist-info/WHEEL
inspect_scout-0.4.11.dist-info/entry_points.txt
inspect_scout-0.4.11.dist-info/licenses/LICENSE
inspect_scout-0.4.11.dist-info/RECORD
